mlnd_distributions/Binomialdistribution.py
mlnd_distributions/Gaussiandistribution.py
mlnd_distributions/Generaldistribution.py
mlnd_distributions/__init__.py
mlnd_distributions-1.0.dist-info/LICENSE
mlnd_distributions-1.0.dist-info/METADATA
mlnd_distributions-1.0.dist-info/WHEEL
mlnd_distributions-1.0.dist-info/top_level.txt
mlnd_distributions-1.0.dist-info/RECORD
