Metadata-Version: 2.1
Name: mlnd-distributions
Version: 1.0
Summary: Gaussian and Binomial distributions
Home-page: https://github.com/demur/mlnd-distributions
Author: Anton Demurenko
Author-email: dai99-uanic@priv.uanic.ua
License: UNKNOWN
Platform: UNKNOWN
Classifier: Programming Language :: Python :: 3
Classifier: License :: OSI Approved :: MIT License
Classifier: Operating System :: OS Independent
